odoo/addons/shopinvader_search_engine_product_stock/README.rst
odoo/addons/shopinvader_search_engine_product_stock/__init__.py
odoo/addons/shopinvader_search_engine_product_stock/__manifest__.py
odoo/addons/shopinvader_search_engine_product_stock/data/queue_job_channel_data.xml
odoo/addons/shopinvader_search_engine_product_stock/data/queue_job_function_data.xml
odoo/addons/shopinvader_search_engine_product_stock/i18n/shopinvader_product_stock.pot
odoo/addons/shopinvader_search_engine_product_stock/i18n/shopinvader_search_engine_product_stock.pot
odoo/addons/shopinvader_search_engine_product_stock/models/__init__.py
odoo/addons/shopinvader_search_engine_product_stock/models/product_product.py
odoo/addons/shopinvader_search_engine_product_stock/models/se_backend.py
odoo/addons/shopinvader_search_engine_product_stock/models/se_index.py
odoo/addons/shopinvader_search_engine_product_stock/models/stock_move.py
odoo/addons/shopinvader_search_engine_product_stock/readme/CONTRIBUTORS.rst
odoo/addons/shopinvader_search_engine_product_stock/readme/CREDITS.rst
odoo/addons/shopinvader_search_engine_product_stock/readme/DESCRIPTION.rst
odoo/addons/shopinvader_search_engine_product_stock/readme/HISTORY.rst
odoo/addons/shopinvader_search_engine_product_stock/schemas/__init__.py
odoo/addons/shopinvader_search_engine_product_stock/schemas/product.py
odoo/addons/shopinvader_search_engine_product_stock/static/description/index.html
odoo/addons/shopinvader_search_engine_product_stock/tests/__init__.py
odoo/addons/shopinvader_search_engine_product_stock/tests/common.py
odoo/addons/shopinvader_search_engine_product_stock/tests/test_product.py
odoo/addons/shopinvader_search_engine_product_stock/tests/test_stock_move.py
odoo/addons/shopinvader_search_engine_product_stock/views/se_backend.xml
odoo/addons/shopinvader_search_engine_product_stock/views/se_index.xml
odoo_addon_shopinvader_search_engine_product_stock-16.0.1.0.4.dist-info/METADATA
odoo_addon_shopinvader_search_engine_product_stock-16.0.1.0.4.dist-info/WHEEL
odoo_addon_shopinvader_search_engine_product_stock-16.0.1.0.4.dist-info/top_level.txt
odoo_addon_shopinvader_search_engine_product_stock-16.0.1.0.4.dist-info/RECORD
